{
    "shop_name": "Thực Vi Thiên - Ẩm Thực Trung Hoa - Trung Hoà",
    "address": "60 Trung Hoà, P. Trung Hoà, Quận Cầu Giấy",
    "menu": [],
    "feedback": [
        {
            "review_point": "7.6",
            "username": "Phuong Anh Cong Chua",
            "describle": "Quán đậm khẩu vị trung quốc, có hơi mặn, nhưng khá chuẩn vị và giá cả phải chăng\nQuán hơi bí, phục vụ nhanh"
        },
        {
            "review_point": "3.8",
            "username": "Linh",
            "describle": "Đồ ăn không ngon, quá nặng về xốt, mỡ và ngọt. Ko hợp khẩu vị Việt. Ghét nhất là bị hun trong khói thuốc lá của hội TQ. Và vô cùng bí với mùi và khói đồ ăn. Đặc trưng quán ăn TQ! Đc mỗi phục vụ."
        },
        {
            "review_point": "6.2",
            "username": "Dung8868",
            "describle": "Đồ ăn 7/10\nPhục vụ 6/10\nNói chung là tạm ổn. Nhưng phục vụ lên đồ quá chậm. Lần nào đến cũng p đợi rất lâu mới có đồ ăn. \nNếu đợi lên đồ ăn lẩu thì p hơn 30’ mới lên đồ. Phục vụ chưa chuyên nghiệp."
        },
        {
            "review_point": "9.8",
            "username": "Hoàng Linh",
            "describle": "Ăn đồ Lào Nhật Âu các kiểu giờ quay sang trải nghiệm đồ ăn Tàu xem sao . Cảm nhận đầu tiên là nhiều mỡ và cay xé mép luôn ấy , ăn cũng ngon và theo mình nên uống thêm bia hay rượu gì đó không ngấy lắm :)"
        }
    ]
}